stacks_page/__init__.py
stacks_page/admin.py
stacks_page/admin_actions.py
stacks_page/apps.py
stacks_page/managers.py
stacks_page/models.py
stacks_page/urls.py
stacks_page/utils.py
stacks_page/views.py
stacks_page/migrations/0001_initial.py
stacks_page/migrations/0002_auto_20150707_2050.py
stacks_page/migrations/0003_auto_20150710_1725.py
stacks_page/migrations/__init__.py
stacks_page/static/js/stacks_page.js
stacks_page/static/sass/stacks_page/_layout.scss
stacks_page/static/sass/stacks_page/_reset.scss
stacks_page/templates/stacks_page/default_page_template.html
stacks_page-0.3.dist-info/DESCRIPTION.rst
stacks_page-0.3.dist-info/LICENSE.txt
stacks_page-0.3.dist-info/METADATA
stacks_page-0.3.dist-info/RECORD
stacks_page-0.3.dist-info/WHEEL
stacks_page-0.3.dist-info/metadata.json
stacks_page-0.3.dist-info/top_level.txt
tests/__init__.py
tests/admin.py
tests/test_settings.py
tests/tests.py
tests/urls.py
